napari_brightness_contrast/__init__.py
napari_brightness_contrast/_dock_widget.py
napari_brightness_contrast/_tests/__init__.py
napari_brightness_contrast/_tests/test_dock_widget.py
napari_brightness_contrast-0.1.8.dist-info/LICENSE
napari_brightness_contrast-0.1.8.dist-info/METADATA
napari_brightness_contrast-0.1.8.dist-info/WHEEL
napari_brightness_contrast-0.1.8.dist-info/entry_points.txt
napari_brightness_contrast-0.1.8.dist-info/top_level.txt
napari_brightness_contrast-0.1.8.dist-info/RECORD
