Metadata-Version: 2.1
Name: napari-brightness-contrast
Version: 0.1.8
Summary: Advanced layer visualization options
Home-page: https://github.com/haesleinhuepf/napari-brightness-contrast
Author: Robert Haase
Author-email: robert.haase@tu-dresden.de
License: BSD-3-Clause
Project-URL: Bug Tracker, https://github.com/haesleinhuepf/napari-brightness-contrast/issues
Project-URL: Documentation, https://github.com/haesleinhuepf/napari-brightness-contrast#README.md
Project-URL: Source Code, https://github.com/haesleinhuepf/napari-brightness-contrast
Project-URL: User Support, https://github.com/haesleinhuepf/napari-brightness-contrast/issues
Classifier: Development Status :: 3 - Alpha
Classifier: Intended Audience :: Developers
Classifier: Framework :: napari
Classifier: Topic :: Scientific/Engineering :: Image Processing
Classifier: Topic :: Scientific/Engineering :: Information Analysis
Classifier: Programming Language :: Python
Classifier: Programming Language :: Python :: 3
Classifier: Programming Language :: Python :: 3.7
Classifier: Programming Language :: Python :: 3.8
Classifier: Programming Language :: Python :: 3.9
Classifier: Operating System :: OS Independent
Classifier: License :: OSI Approved :: BSD License
Requires-Python: >=3.7
License-File: LICENSE
Requires-Dist: napari-plugin-engine (>=0.1.4)
Requires-Dist: napari
Requires-Dist: numpy
Requires-Dist: pyqtgraph
Requires-Dist: superqt
Requires-Dist: napari-tools-menu
Provides-Extra: tests
Requires-Dist: pytest ; extra == 'tests'
Requires-Dist: pytest-qt ; extra == 'tests'
